dupfilesremover/__init__.py
dupfilesremover/__main__.py
dupfilesremover/app.py
dupfilesremover/version.py
dupfilesremover/command_line/__init__.py
dupfilesremover/command_line/dupfilesremover.py
dupfilesremover/implementation/__init__.py
dupfilesremover/implementation/duplicate_files_remover.py
dupfilesremover-0.2.6.0.dist-info/LICENSE
dupfilesremover-0.2.6.0.dist-info/METADATA
dupfilesremover-0.2.6.0.dist-info/WHEEL
dupfilesremover-0.2.6.0.dist-info/entry_points.txt
dupfilesremover-0.2.6.0.dist-info/top_level.txt
dupfilesremover-0.2.6.0.dist-info/RECORD
