Metadata-Version: 2.1
Name: dupfilesremover
Version: 0.2.6.0
Summary: Module to support VRC-T70 hardware
Home-page: https://github.com/JFF-Bohdan/dupfilesremover
Author: Bohdan Danishevsky
Author-email: dbn@aminis.com.ua
License: MIT
Keywords: duplicates remover,duplicate images remover,dups remover
Platform: UNKNOWN
Requires-Dist: loguru
Requires-Dist: terminaltables (==3.1.0)
Requires-Dist: tqdm (==4.31.1)
